{"name":"CUELLOBAUTEALFREDOAPE","name_key":"CUELLOBAUTEALFREDOAPE","photo":"fotos/colombia/rep_col_alfredo_ape_cuello_baute.png","chambers":["camara_col"],"chamber":"camara_col","bloc":"Partido Conservador Colombiano","province":"Cesar","coalition":"CONSERVADOR","yearly_stats":{"2025":{"AFIRMATIVO":5,"NEGATIVO":1,"ABSTENCION":16,"AUSENTE":0,"PRESIDENTE":0,"total":22}},"trailing_ausente":0,"yearly_alignment":{"2025":{"PACTO":50.0,"LIBERAL":75.0,"CONSERVADOR":62.5,"CD":25.0}},"alignment":{"PACTO":50.0,"LIBERAL":75.0,"CONSERVADOR":62.5,"CD":25.0},"era_alignment":{"2018-2022":{"CD":null},"2022-2026":{"PACTO":50.0}},"terms":[{"ch":"camara_col","yf":2025,"yt":2025,"b":"Partido Conservador Colombiano","p":"Cesar","co_electoral":"CONSERVADOR","alliance":null,"co":"CONSERVADOR"}],"votes":[{"vid":"123913_1","ch":"camara_col","t":"PROPOSICIONESMODIFICACIÓNORDENDELDÍA","d":"28/10/2025","yr":2025,"v":"ABSTENCION","tp":"EN GENERAL","gk":"camara_col|PROPOSICIONESMODIFICACIÓNORDENDELDÍA|28/10/2025","ln":"PROPOSICIONESMODIFICACIÓNORDENDELDÍA","cn":null,"al":"En General"},{"vid":"123913_2","ch":"camara_col","t":"PL.333/24PROFESIONALENCONSTRUCCIÓN-IMPEDIMENTOSHRCARLOSARDILAY OTROS","d":"28/10/2025","yr":2025,"v":"ABSTENCION","tp":"EN GENERAL","gk":"camara_col|PL.333/24PROFESIONALENCONSTRUCCIÓN-IMPEDIMENTOSHRCARLOSARDILAY OTROS|28/10/2025","ln":"PL.333/24PROFESIONALENCONSTRUCCIÓN-IMPEDIMENTOSHRCARLOSARDILAY OTROS","cn":null,"al":"En General"},{"vid":"123913_3","ch":"camara_col","t":"PL.333/24PROFESIONALENCONSTRUCCIÓN-INFORMEDEPONENCIA","d":"28/10/2025","yr":2025,"v":"ABSTENCION","tp":"EN GENERAL","gk":"camara_col|PL.333/24PROFESIONALENCONSTRUCCIÓN-INFORMEDEPONENCIA|28/10/2025","ln":"PL.333/24PROFESIONALENCONSTRUCCIÓN-INFORMEDEPONENCIA","cn":null,"al":"En General"},{"vid":"123913_4","ch":"camara_col","t":"PL.333/24PROFESIONALENCONSTRUCCIÓN-ARTICULADO","d":"28/10/2025","yr":2025,"v":"AFIRMATIVO","tp":"EN GENERAL","gk":"camara_col|PL.333/24PROFESIONALENCONSTRUCCIÓN-ARTICULADO|28/10/2025","ln":"PL.333/24PROFESIONALENCONSTRUCCIÓN-ARTICULADO","cn":null,"al":"En General"},{"vid":"123913_5","ch":"camara_col","t":"PL.333/24PROFESIONALENCONSTRUCCIÓN-ARTÍCULOSNUEVOS","d":"28/10/2025","yr":2025,"v":"AFIRMATIVO","tp":"EN GENERAL","gk":"camara_col|PL.333/24PROFESIONALENCONSTRUCCIÓN-ARTÍCULOSNUEVOS|28/10/2025","ln":"PL.333/24PROFESIONALENCONSTRUCCIÓN-ARTÍCULOSNUEVOS","cn":null,"al":"En General"},{"vid":"123913_6","ch":"camara_col","t":"PL.333/24PROFESIONALENCONSTRUCCIÓN-TÍTULOYPREGUNTA","d":"28/10/2025","yr":2025,"v":"AFIRMATIVO","tp":"EN GENERAL","gk":"camara_col|PL.333/24PROFESIONALENCONSTRUCCIÓN-TÍTULOYPREGUNTA|28/10/2025","ln":"PL.333/24PROFESIONALENCONSTRUCCIÓN-TÍTULOYPREGUNTA","cn":null,"al":"En General"},{"vid":"123913_7","ch":"camara_col","t":"PL.466/24LEYNUCLEAR-INFORMEDEPONENCIA","d":"28/10/2025","yr":2025,"v":"ABSTENCION","tp":"EN GENERAL","gk":"camara_col|PL.466/24LEYNUCLEAR-INFORMEDEPONENCIA|28/10/2025","ln":"PL.466/24LEYNUCLEAR-INFORMEDEPONENCIA","cn":null,"al":"En General"},{"vid":"123913_8","ch":"camara_col","t":"PL.466/24LEYNUCLEAR-ARTICULADO","d":"28/10/2025","yr":2025,"v":"ABSTENCION","tp":"EN GENERAL","gk":"camara_col|PL.466/24LEYNUCLEAR-ARTICULADO|28/10/2025","ln":"PL.466/24LEYNUCLEAR-ARTICULADO","cn":null,"al":"En General"},{"vid":"123913_9","ch":"camara_col","t":"PL.466/24LEYNUCLEAR-TÍTULOYPREGUNTA","d":"28/10/2025","yr":2025,"v":"ABSTENCION","tp":"EN GENERAL","gk":"camara_col|PL.466/24LEYNUCLEAR-TÍTULOYPREGUNTA|28/10/2025","ln":"PL.466/24LEYNUCLEAR-TÍTULOYPREGUNTA","cn":null,"al":"En General"},{"vid":"123913_10","ch":"camara_col","t":"SESIÓNPERMANENTE(SUSPENDIDA)","d":"28/10/2025","yr":2025,"v":"ABSTENCION","tp":"EN GENERAL","gk":"camara_col|SESIÓNPERMANENTE(SUSPENDIDA)|28/10/2025","ln":"SESIÓNPERMANENTE(SUSPENDIDA)","cn":null,"al":"En General"},{"vid":"124202_1","ch":"camara_col","t":"PROPOSICIONESDEMODIFICACIÓNDELORDENDELDÍA","d":"29/10/2025","yr":2025,"v":"ABSTENCION","tp":"EN GENERAL","gk":"camara_col|PROPOSICIONESDEMODIFICACIÓNDELORDENDELDÍA|29/10/2025","ln":"PROPOSICIONESDEMODIFICACIÓNDELORDENDELDÍA","cn":null,"al":"En General"},{"vid":"124202_2","ch":"camara_col","t":"PL.625/25PROTOCOLOPERSONASCONDISCAPACIDAD-INFORMEDEPONENCIA","d":"29/10/2025","yr":2025,"v":"AFIRMATIVO","tp":"EN GENERAL","gk":"camara_col|PL.625/25PROTOCOLOPERSONASCONDISCAPACIDAD-INFORMEDEPONENCIA|29/10/2025","ln":"PL.625/25PROTOCOLOPERSONASCONDISCAPACIDAD-INFORMEDEPONENCIA","cn":null,"al":"En General"},{"vid":"124202_3","ch":"camara_col","t":"PL.625/25PROTOCOLOPERSONASCONDISCAPACIDAD-ARTICULADO","d":"29/10/2025","yr":2025,"v":"ABSTENCION","tp":"EN GENERAL","gk":"camara_col|PL.625/25PROTOCOLOPERSONASCONDISCAPACIDAD-ARTICULADO|29/10/2025","ln":"PL.625/25PROTOCOLOPERSONASCONDISCAPACIDAD-ARTICULADO","cn":null,"al":"En General"},{"vid":"124202_4","ch":"camara_col","t":"PL.625/25PROTOCOLOPERSONASCONDISCAPACIDAD-TÍTULOYPREGUNTA","d":"29/10/2025","yr":2025,"v":"ABSTENCION","tp":"EN GENERAL","gk":"camara_col|PL.625/25PROTOCOLOPERSONASCONDISCAPACIDAD-TÍTULOYPREGUNTA|29/10/2025","ln":"PL.625/25PROTOCOLOPERSONASCONDISCAPACIDAD-TÍTULOYPREGUNTA","cn":null,"al":"En General"},{"vid":"124202_5","ch":"camara_col","t":"PL.541/25LEYEMPATÍA-IMPEDIMENTOHRJUANCAMILOLONDOÑO","d":"29/10/2025","yr":2025,"v":"ABSTENCION","tp":"EN GENERAL","gk":"camara_col|PL.541/25LEYEMPATÍA-IMPEDIMENTOHRJUANCAMILOLONDOÑO|29/10/2025","ln":"PL.541/25LEYEMPATÍA-IMPEDIMENTOHRJUANCAMILOLONDOÑO","cn":null,"al":"En General"},{"vid":"124585_1","ch":"camara_col","t":"PL.398/24JURISDICCIÓNAGRARIA-IMPEDIMENTOSHRMARÍAEUGENIALOPERAY OTROS","d":"18/11/2025","yr":2025,"v":"ABSTENCION","tp":"EN GENERAL","gk":"camara_col|PL.398/24JURISDICCIÓNAGRARIA-IMPEDIMENTOSHRMARÍAEUGENIALOPERAY OTROS|18/11/2025","ln":"PL.398/24JURISDICCIÓNAGRARIA-IMPEDIMENTOSHRMARÍAEUGENIALOPERAY OTROS","cn":null,"al":"En General"},{"vid":"124585_2","ch":"camara_col","t":"PL.398/24JURISDICCIÓNAGRARIA-IMPEDIMENTOHRCARLOSALBERTOCUENCA","d":"18/11/2025","yr":2025,"v":"AFIRMATIVO","tp":"EN GENERAL","gk":"camara_col|PL.398/24JURISDICCIÓNAGRARIA-IMPEDIMENTOHRCARLOSALBERTOCUENCA|18/11/2025","ln":"PL.398/24JURISDICCIÓNAGRARIA-IMPEDIMENTOHRCARLOSALBERTOCUENCA","cn":null,"al":"En General"},{"vid":"124585_3","ch":"camara_col","t":"PL.398/24JURISDICCIÓNAGRARIA-IMPEDIMENTOSHRKELYNJOHANAGONZALEZY OTROS","d":"18/11/2025","yr":2025,"v":"NEGATIVO","tp":"EN GENERAL","gk":"camara_col|PL.398/24JURISDICCIÓNAGRARIA-IMPEDIMENTOSHRKELYNJOHANAGONZALEZY OTROS|18/11/2025","ln":"PL.398/24JURISDICCIÓNAGRARIA-IMPEDIMENTOSHRKELYNJOHANAGONZALEZY OTROS","cn":null,"al":"En General"},{"vid":"124585_4","ch":"camara_col","t":"PL.398/24JURISDICCIÓNAGRARIA-IMPEDIMENTOSHRGILMADÍAZYOTROS","d":"18/11/2025","yr":2025,"v":"ABSTENCION","tp":"EN GENERAL","gk":"camara_col|PL.398/24JURISDICCIÓNAGRARIA-IMPEDIMENTOSHRGILMADÍAZYOTROS|18/11/2025","ln":"PL.398/24JURISDICCIÓNAGRARIA-IMPEDIMENTOSHRGILMADÍAZYOTROS","cn":null,"al":"En General"},{"vid":"124585_5","ch":"camara_col","t":"PL.398/24JURISDICCIÓNAGRARIA-IMPEDIMENTOSHRDIEGOPATIÑOAMARILESY OTROS(SUSPENDIDA)","d":"18/11/2025","yr":2025,"v":"ABSTENCION","tp":"EN GENERAL","gk":"camara_col|PL.398/24JURISDICCIÓNAGRARIA-IMPEDIMENTOSHRDIEGOPATIÑOAMARILESY OTROS(SUSPENDIDA)|18/11/2025","ln":"PL.398/24JURISDICCIÓNAGRARIA-IMPEDIMENTOSHRDIEGOPATIÑOAMARILESY OTROS(SUSPENDIDA)","cn":null,"al":"En General"},{"vid":"124586_1","ch":"camara_col","t":"PL.514/25UNIVERSIDADNACIONALDELCATATUMBO-INFORMEDEPONENCIA (SUSPENDIDA)","d":"26/11/2025","yr":2025,"v":"ABSTENCION","tp":"EN GENERAL","gk":"camara_col|PL.514/25UNIVERSIDADNACIONALDELCATATUMBO-INFORMEDEPONENCIA (SUSPENDIDA)|26/11/2025","ln":"PL.514/25UNIVERSIDADNACIONALDELCATATUMBO-INFORMEDEPONENCIA (SUSPENDIDA)","cn":null,"al":"En General"},{"vid":"124586_2","ch":"camara_col","t":"PLE.083/25FORTALECIMIENTOCONSEJOSDEJUVENTUD-INFORMEDEPONENCIA","d":"26/11/2025","yr":2025,"v":"ABSTENCION","tp":"EN GENERAL","gk":"camara_col|PLE.083/25FORTALECIMIENTOCONSEJOSDEJUVENTUD-INFORMEDEPONENCIA|26/11/2025","ln":"PLE.083/25FORTALECIMIENTOCONSEJOSDEJUVENTUD-INFORMEDEPONENCIA","cn":null,"al":"En General"}],"laws":[{"gk":"camara_col|PL.333/24PROFESIONALENCONSTRUCCIÓN-ARTICULADO|28/10/2025","name":"PL.333/24PROFESIONALENCONSTRUCCIÓN-ARTICULADO","year":2025,"url":"","votes":[{"v":"AFIRMATIVO","al":"En General","t":"PL.333/24PROFESIONALENCONSTRUCCIÓN-ARTICULADO","vid":"123913_4","ch":"camara_col","g":true}],"notable":false},{"gk":"camara_col|PL.333/24PROFESIONALENCONSTRUCCIÓN-ARTÍCULOSNUEVOS|28/10/2025","name":"PL.333/24PROFESIONALENCONSTRUCCIÓN-ARTÍCULOSNUEVOS","year":2025,"url":"","votes":[{"v":"AFIRMATIVO","al":"En General","t":"PL.333/24PROFESIONALENCONSTRUCCIÓN-ARTÍCULOSNUEVOS","vid":"123913_5","ch":"camara_col","g":true}],"notable":false},{"gk":"camara_col|PL.333/24PROFESIONALENCONSTRUCCIÓN-IMPEDIMENTOSHRCARLOSARDILAY OTROS|28/10/2025","name":"PL.333/24PROFESIONALENCONSTRUCCIÓN-IMPEDIMENTOSHRCARLOSARDILAY OTROS","year":2025,"url":"","votes":[{"v":"ABSTENCION","al":"En General","t":"PL.333/24PROFESIONALENCONSTRUCCIÓN-IMPEDIMENTOSHRCARLOSARDILAY OTROS","vid":"123913_2","ch":"camara_col","g":true}],"notable":false},{"gk":"camara_col|PL.333/24PROFESIONALENCONSTRUCCIÓN-INFORMEDEPONENCIA|28/10/2025","name":"PL.333/24PROFESIONALENCONSTRUCCIÓN-INFORMEDEPONENCIA","year":2025,"url":"","votes":[{"v":"ABSTENCION","al":"En General","t":"PL.333/24PROFESIONALENCONSTRUCCIÓN-INFORMEDEPONENCIA","vid":"123913_3","ch":"camara_col","g":true}],"notable":false},{"gk":"camara_col|PL.333/24PROFESIONALENCONSTRUCCIÓN-TÍTULOYPREGUNTA|28/10/2025","name":"PL.333/24PROFESIONALENCONSTRUCCIÓN-TÍTULOYPREGUNTA","year":2025,"url":"","votes":[{"v":"AFIRMATIVO","al":"En General","t":"PL.333/24PROFESIONALENCONSTRUCCIÓN-TÍTULOYPREGUNTA","vid":"123913_6","ch":"camara_col","g":true}],"notable":false},{"gk":"camara_col|PL.398/24JURISDICCIÓNAGRARIA-IMPEDIMENTOHRCARLOSALBERTOCUENCA|18/11/2025","name":"PL.398/24JURISDICCIÓNAGRARIA-IMPEDIMENTOHRCARLOSALBERTOCUENCA","year":2025,"url":"","votes":[{"v":"AFIRMATIVO","al":"En General","t":"PL.398/24JURISDICCIÓNAGRARIA-IMPEDIMENTOHRCARLOSALBERTOCUENCA","vid":"124585_2","ch":"camara_col","g":true}],"notable":false},{"gk":"camara_col|PL.398/24JURISDICCIÓNAGRARIA-IMPEDIMENTOSHRDIEGOPATIÑOAMARILESY OTROS(SUSPENDIDA)|18/11/2025","name":"PL.398/24JURISDICCIÓNAGRARIA-IMPEDIMENTOSHRDIEGOPATIÑOAMARILESY OTROS(SUSPENDIDA)","year":2025,"url":"","votes":[{"v":"ABSTENCION","al":"En General","t":"PL.398/24JURISDICCIÓNAGRARIA-IMPEDIMENTOSHRDIEGOPATIÑOAMARILESY OTROS(SUSPENDIDA)","vid":"124585_5","ch":"camara_col","g":true}],"notable":false},{"gk":"camara_col|PL.398/24JURISDICCIÓNAGRARIA-IMPEDIMENTOSHRGILMADÍAZYOTROS|18/11/2025","name":"PL.398/24JURISDICCIÓNAGRARIA-IMPEDIMENTOSHRGILMADÍAZYOTROS","year":2025,"url":"","votes":[{"v":"ABSTENCION","al":"En General","t":"PL.398/24JURISDICCIÓNAGRARIA-IMPEDIMENTOSHRGILMADÍAZYOTROS","vid":"124585_4","ch":"camara_col","g":true}],"notable":false},{"gk":"camara_col|PL.398/24JURISDICCIÓNAGRARIA-IMPEDIMENTOSHRKELYNJOHANAGONZALEZY OTROS|18/11/2025","name":"PL.398/24JURISDICCIÓNAGRARIA-IMPEDIMENTOSHRKELYNJOHANAGONZALEZY OTROS","year":2025,"url":"","votes":[{"v":"NEGATIVO","al":"En General","t":"PL.398/24JURISDICCIÓNAGRARIA-IMPEDIMENTOSHRKELYNJOHANAGONZALEZY OTROS","vid":"124585_3","ch":"camara_col","g":true}],"notable":false},{"gk":"camara_col|PL.398/24JURISDICCIÓNAGRARIA-IMPEDIMENTOSHRMARÍAEUGENIALOPERAY OTROS|18/11/2025","name":"PL.398/24JURISDICCIÓNAGRARIA-IMPEDIMENTOSHRMARÍAEUGENIALOPERAY OTROS","year":2025,"url":"","votes":[{"v":"ABSTENCION","al":"En General","t":"PL.398/24JURISDICCIÓNAGRARIA-IMPEDIMENTOSHRMARÍAEUGENIALOPERAY OTROS","vid":"124585_1","ch":"camara_col","g":true}],"notable":false},{"gk":"camara_col|PL.466/24LEYNUCLEAR-ARTICULADO|28/10/2025","name":"PL.466/24LEYNUCLEAR-ARTICULADO","year":2025,"url":"","votes":[{"v":"ABSTENCION","al":"En General","t":"PL.466/24LEYNUCLEAR-ARTICULADO","vid":"123913_8","ch":"camara_col","g":true}],"notable":false},{"gk":"camara_col|PL.466/24LEYNUCLEAR-INFORMEDEPONENCIA|28/10/2025","name":"PL.466/24LEYNUCLEAR-INFORMEDEPONENCIA","year":2025,"url":"","votes":[{"v":"ABSTENCION","al":"En General","t":"PL.466/24LEYNUCLEAR-INFORMEDEPONENCIA","vid":"123913_7","ch":"camara_col","g":true}],"notable":false},{"gk":"camara_col|PL.466/24LEYNUCLEAR-TÍTULOYPREGUNTA|28/10/2025","name":"PL.466/24LEYNUCLEAR-TÍTULOYPREGUNTA","year":2025,"url":"","votes":[{"v":"ABSTENCION","al":"En General","t":"PL.466/24LEYNUCLEAR-TÍTULOYPREGUNTA","vid":"123913_9","ch":"camara_col","g":true}],"notable":false},{"gk":"camara_col|PL.514/25UNIVERSIDADNACIONALDELCATATUMBO-INFORMEDEPONENCIA (SUSPENDIDA)|26/11/2025","name":"PL.514/25UNIVERSIDADNACIONALDELCATATUMBO-INFORMEDEPONENCIA (SUSPENDIDA)","year":2025,"url":"","votes":[{"v":"ABSTENCION","al":"En General","t":"PL.514/25UNIVERSIDADNACIONALDELCATATUMBO-INFORMEDEPONENCIA (SUSPENDIDA)","vid":"124586_1","ch":"camara_col","g":true}],"notable":false},{"gk":"camara_col|PL.541/25LEYEMPATÍA-IMPEDIMENTOHRJUANCAMILOLONDOÑO|29/10/2025","name":"PL.541/25LEYEMPATÍA-IMPEDIMENTOHRJUANCAMILOLONDOÑO","year":2025,"url":"","votes":[{"v":"ABSTENCION","al":"En General","t":"PL.541/25LEYEMPATÍA-IMPEDIMENTOHRJUANCAMILOLONDOÑO","vid":"124202_5","ch":"camara_col","g":true}],"notable":false},{"gk":"camara_col|PL.625/25PROTOCOLOPERSONASCONDISCAPACIDAD-ARTICULADO|29/10/2025","name":"PL.625/25PROTOCOLOPERSONASCONDISCAPACIDAD-ARTICULADO","year":2025,"url":"","votes":[{"v":"ABSTENCION","al":"En General","t":"PL.625/25PROTOCOLOPERSONASCONDISCAPACIDAD-ARTICULADO","vid":"124202_3","ch":"camara_col","g":true}],"notable":false},{"gk":"camara_col|PL.625/25PROTOCOLOPERSONASCONDISCAPACIDAD-INFORMEDEPONENCIA|29/10/2025","name":"PL.625/25PROTOCOLOPERSONASCONDISCAPACIDAD-INFORMEDEPONENCIA","year":2025,"url":"","votes":[{"v":"AFIRMATIVO","al":"En General","t":"PL.625/25PROTOCOLOPERSONASCONDISCAPACIDAD-INFORMEDEPONENCIA","vid":"124202_2","ch":"camara_col","g":true}],"notable":false},{"gk":"camara_col|PL.625/25PROTOCOLOPERSONASCONDISCAPACIDAD-TÍTULOYPREGUNTA|29/10/2025","name":"PL.625/25PROTOCOLOPERSONASCONDISCAPACIDAD-TÍTULOYPREGUNTA","year":2025,"url":"","votes":[{"v":"ABSTENCION","al":"En General","t":"PL.625/25PROTOCOLOPERSONASCONDISCAPACIDAD-TÍTULOYPREGUNTA","vid":"124202_4","ch":"camara_col","g":true}],"notable":false},{"gk":"camara_col|PLE.083/25FORTALECIMIENTOCONSEJOSDEJUVENTUD-INFORMEDEPONENCIA|26/11/2025","name":"PLE.083/25FORTALECIMIENTOCONSEJOSDEJUVENTUD-INFORMEDEPONENCIA","year":2025,"url":"","votes":[{"v":"ABSTENCION","al":"En General","t":"PLE.083/25FORTALECIMIENTOCONSEJOSDEJUVENTUD-INFORMEDEPONENCIA","vid":"124586_2","ch":"camara_col","g":true}],"notable":false},{"gk":"camara_col|PROPOSICIONESDEMODIFICACIÓNDELORDENDELDÍA|29/10/2025","name":"PROPOSICIONESDEMODIFICACIÓNDELORDENDELDÍA","year":2025,"url":"","votes":[{"v":"ABSTENCION","al":"En General","t":"PROPOSICIONESDEMODIFICACIÓNDELORDENDELDÍA","vid":"124202_1","ch":"camara_col","g":true}],"notable":false},{"gk":"camara_col|PROPOSICIONESMODIFICACIÓNORDENDELDÍA|28/10/2025","name":"PROPOSICIONESMODIFICACIÓNORDENDELDÍA","year":2025,"url":"","votes":[{"v":"ABSTENCION","al":"En General","t":"PROPOSICIONESMODIFICACIÓNORDENDELDÍA","vid":"123913_1","ch":"camara_col","g":true}],"notable":false},{"gk":"camara_col|SESIÓNPERMANENTE(SUSPENDIDA)|28/10/2025","name":"SESIÓNPERMANENTE(SUSPENDIDA)","year":2025,"url":"","votes":[{"v":"ABSTENCION","al":"En General","t":"SESIÓNPERMANENTE(SUSPENDIDA)","vid":"123913_10","ch":"camara_col","g":true}],"notable":false}]}